setup.py
dist_binomial_gaussian.egg-info/PKG-INFO
dist_binomial_gaussian.egg-info/SOURCES.txt
dist_binomial_gaussian.egg-info/dependency_links.txt
dist_binomial_gaussian.egg-info/not-zip-safe
dist_binomial_gaussian.egg-info/top_level.txt
distributions/Binomialdistribution.py
distributions/Gaussiandistribution.py
distributions/Generaldistribution.py
distributions/__init__.py