Metadata-Version: 1.0
Name: dist-binomial-gaussian
Version: 0.1
Summary: Gaussian distributions
Home-page: UNKNOWN
Author: Chanakarn Luangpirom
Author-email: UNKNOWN
License: UNKNOWN
Platform: UNKNOWN
